{
  "$schema": "../schemas/character.schema.json",
  "id": "1412",
  "slug": "cerydra",
  "gameId": "1412",
  "name": "Cerydra",
  "rarity": 5,
  "element": "wind",
  "path": "harmony",
  "level": 80,
  "maxSp": 130,
  "baseStats": {
    "atk": 620.93,
    "hp": 1358.28,
    "def": 485.1,
    "speed": 99,
    "critRate": 0.05,
    "critDmg": 0.5
  },
  "traces": {
    "hpPercent": 0.1,
    "elementDmgBonus": 0.224,
    "atkPercent": 0.18
  },
  "tracesRaw": {
    "HP%": 0.1,
    "Wind DMG Boost": 0.224,
    "ATK%": 0.18
  },
  "traceModifiers": [
    {
      "zones": [
        "atk_percent"
      ],
      "value": 0.18
    },
    {
      "zones": [
        "dmg_bonus"
      ],
      "value": 0.224,
      "tagFilter": [
        "wind"
      ]
    }
  ],
  "skills": {
    "basic": {
      "id": "basic",
      "name": "普攻",
      "type": "direct",
      "multiplier": 1,
      "tags": [
        "basic"
      ]
    },
    "skill": {
      "id": "skill",
      "name": "战技",
      "type": "direct",
      "multiplier": 1,
      "tags": [
        "skill"
      ]
    },
    "ult": {
      "id": "ult",
      "name": "终结技",
      "type": "direct",
      "multiplier": 1,
      "tags": [
        "ult"
      ]
    }
  },
  "passives": [
    {
      "zones": [
        "atk_percent"
      ],
      "value": 0.18
    },
    {
      "zones": [
        "dmg_bonus"
      ],
      "value": 0.224,
      "tagFilter": [
        "wind"
      ]
    }
  ],
  "source": "hsr-optimizer"
}