{
  "$schema": "../schemas/light_cone.schema.json",
  "id": "21055",
  "slug": "unto-tomorrow-s-morrow",
  "gameId": "21055",
  "name": "Unto Tomorrow's Morrow",
  "rarity": 4,
  "path": "abundance",
  "level": 80,
  "superimposition": 1,
  "baseStats": {
    "atk": 476.28,
    "hp": 1058.4,
    "def": 396.9
  },
  "superimpositions": {
    "1": {
      "HealRatioBase": 0.12
    },
    "2": {
      "HealRatioBase": 0.15
    },
    "3": {
      "HealRatioBase": 0.18
    },
    "4": {
      "HealRatioBase": 0.21
    },
    "5": {
      "HealRatioBase": 0.24
    }
  },
  "passive": null,
  "source": "hsr-optimizer"
}